pyharm/_constants.py
pyharm/libcharm.cpython-313-darwin.so
pyharm/misc.py
pyharm/_formatting.py
pyharm/_encoding.py
pyharm/_data_types.py
pyharm/_err.py
pyharm/shc.py
pyharm/_check_types.py
pyharm/integ.py
pyharm/__init__.py
pyharm/glob.py
pyharm/sha.py
pyharm/_get_module_constants.py
pyharm/gfm.py
pyharm/_get_empty_array.py
pyharm/shs.py
pyharm/crd.py
pyharm/leg.py
pyharm/_lib.py
pyharm/.dylibs/libomp.dylib
pyharm/.dylibs/libfftw3_omp.3.dylib
pyharm/.dylibs/libfftw3.3.dylib
pyharm/.dylibs/libgmp.10.dylib
pyharm/.dylibs/libmpfr.6.dylib
pyharm-0.4.8.dist-info/RECORD
pyharm-0.4.8.dist-info/WHEEL
pyharm-0.4.8.dist-info/top_level.txt
pyharm-0.4.8.dist-info/METADATA
pyharm-0.4.8.dist-info/licenses/AUTHORS
pyharm-0.4.8.dist-info/licenses/COPYING
