Metadata-Version: 2.4
Name: pyharm
Version: 0.4.8
Summary: Python wrapper for CHarm, a C library to work with spherical harmonics up to almost arbitrarily high degrees
Home-page: https://github.com/blazej-bucha/charm
Author: Blazej Bucha
Author-email: blazej.bucha@stuba.sk
License-File: AUTHORS
License-File: COPYING
Requires-Dist: numpy
Dynamic: author
Dynamic: author-email
Dynamic: description
Dynamic: description-content-type
Dynamic: home-page
Dynamic: license-file
Dynamic: requires-dist
Dynamic: summary
